melisa/__init__.py
melisa/cache.py
melisa/client.py
melisa/exceptions.py
melisa/rest.py
melisa/core/__init__.py
melisa/core/gateway.py
melisa/core/http.py
melisa/core/ratelimiter.py
melisa/listeners/__init__.py
melisa/listeners/channel_create.py
melisa/listeners/channel_delete.py
melisa/listeners/channel_update.py
melisa/listeners/guild_create.py
melisa/listeners/guild_remove.py
melisa/listeners/guild_update.py
melisa/listeners/message_create.py
melisa/listeners/ready.py
melisa/models/__init__.py
melisa/models/app/__init__.py
melisa/models/app/intents.py
melisa/models/app/shard.py
melisa/models/guild/__init__.py
melisa/models/guild/channel.py
melisa/models/guild/emoji.py
melisa/models/guild/guild.py
melisa/models/guild/member.py
melisa/models/guild/role.py
melisa/models/guild/thread.py
melisa/models/guild/webhook.py
melisa/models/message/__init__.py
melisa/models/message/colors.py
melisa/models/message/embed.py
melisa/models/message/file.py
melisa/models/message/message.py
melisa/models/user/__init__.py
melisa/models/user/presence.py
melisa/models/user/user.py
melisa/utils/__init__.py
melisa/utils/api_model.py
melisa/utils/conversion.py
melisa/utils/json.py
melisa/utils/logging.py
melisa/utils/snowflake.py
melisa/utils/timestamp.py
melisa/utils/types.py
melisa/utils/waiters.py
tests/__init__.py
tests/test_caching.py
tests/test_colors.py
tests/test_embeds.py
tests/test_snowflakes.py
melisa-0.0.1.dev1.dist-info/LICENSE.txt
melisa-0.0.1.dev1.dist-info/METADATA
melisa-0.0.1.dev1.dist-info/WHEEL
melisa-0.0.1.dev1.dist-info/top_level.txt
melisa-0.0.1.dev1.dist-info/RECORD
