Metadata-Version: 2.1
Name: melisa
Version: 0.0.1.dev1
Summary: Cache-optimized Discord microframework for Python 3
Home-page: https://github.com/MelisaDev/melisa
Author: MelisaDev
License: MIT
Project-URL: Documentation, https://docs.melisapy.site/
Project-URL: Source (GitHub), https://github.com/MelisaDev/melisa
Project-URL: Discord, https://discord.gg/QX4EG8f7aD
Classifier: License :: OSI Approved :: MIT License
Classifier: Intended Audience :: Developers
Classifier: Natural Language :: English
Classifier: Operating System :: OS Independent
Classifier: Programming Language :: Python :: 3.8
Classifier: Programming Language :: Python :: 3.9
Classifier: Programming Language :: Python :: 3.10
Classifier: Programming Language :: Python :: Implementation :: CPython
Classifier: Topic :: Communications :: Chat
Classifier: Topic :: Internet :: WWW/HTTP
Classifier: Topic :: Internet
Classifier: Topic :: Software Development :: Libraries
Classifier: Topic :: Software Development :: Libraries :: Application Frameworks
Classifier: Topic :: Software Development :: Libraries :: Python Modules
Classifier: Topic :: Utilities
Classifier: Typing :: Typed
Requires-Python: >=3.8,<3.11
License-File: LICENSE.txt
Requires-Dist: aiohttp
Requires-Dist: typing-extensions
Provides-Extra: speedup
Requires-Dist: orjson (==3.6.8) ; extra == 'speedup'
